saxs_single_bead/__init__.py
saxs_single_bead/form_factors.py
saxs_single_bead/read_pdb.py
saxs_single_bead/replace_bead.py
saxs_single_bead/scattering_curve.py
saxs_single_bead-0.0.3.dist-info/LICENSE
saxs_single_bead-0.0.3.dist-info/METADATA
saxs_single_bead-0.0.3.dist-info/WHEEL
saxs_single_bead-0.0.3.dist-info/top_level.txt
saxs_single_bead-0.0.3.dist-info/RECORD
