Metadata-Version: 2.1
Name: saxs-single-bead
Version: 0.0.3
Summary: All Python package to compute small angle X-ray scattering (SAXS) profiles in one-bead-per-residue approximation with numpy
Home-page: https://github.com/RadostW/saxs_single_bead/
Author: Radost Waszkiewicz
Author-email: radost.waszkiewicz@gmail.com
License: MIT
Project-URL: Documentation, https://saxs_single_bead.readthedocs.io
Project-URL: Source, https://github.com/RadostW/saxs_single_bead/
License-File: LICENSE
